README
setup.cfg
setup.py
LibSerial26/LibSerial26.py
LibSerial26/__init__.py
LibSerial26.egg-info/PKG-INFO
LibSerial26.egg-info/SOURCES.txt
LibSerial26.egg-info/dependency_links.txt
LibSerial26.egg-info/requires.txt
LibSerial26.egg-info/top_level.txt