Metadata-Version: 1.1
Name: LibSerial26
Version: 0.5
Summary: Biblioteca LibSerial26
Home-page: https://github.com/renoh/LibSerial26
Author: Henrique Reno Sawada
Author-email: renohh@gmail.com
License: MIT
Download-URL: https://github.com/renoh/LibSerial26/archive/0.3.tar.gz
Keywords: Serial,SENAI,COMPort
Platform: UNKNOWN
Classifier: Development Status :: 5 - Production/Stable
Classifier: Intended Audience :: Developers
Classifier: Topic :: Software Development :: Build Tools
Classifier: License :: OSI Approved :: MIT License
Classifier: Programming Language :: Python :: 3
Classifier: Programming Language :: Python :: 3.7
Classifier: Programming Language :: Python :: 3.8
